AUTHORS.rst
CHANGES.rst
LICENSE-MIT
MANIFEST.in
README.rst
django-messages-ui.jquery.json
setup.cfg
setup.py
django_messages_ui.egg-info/PKG-INFO
django_messages_ui.egg-info/SOURCES.txt
django_messages_ui.egg-info/dependency_links.txt
django_messages_ui.egg-info/not-zip-safe
django_messages_ui.egg-info/top_level.txt
messages_ui/middleware.py
messages_ui/models.py
messages_ui/tests.py
messages_ui/jstemplates/message.html
messages_ui/static/messages_ui/django-messages-ui.js
messages_ui/static/messages_ui/message.js
messages_ui/templates/messages_ui/_messages.html
messages_ui/templates/messages_ui/_messages_ich.html