Metadata-Version: 1.1
Name: django-messages-ui
Version: 1.0.1
Summary: JS client-side messages plugin, with support for Django contrib.messages app
Home-page: https://github.com/jgerigmeyer/jquery-django-messages-ui/
Author: Jonny Gerig Meyer
Author-email: jonny@oddbird.net
License: UNKNOWN
Platform: UNKNOWN
Classifier: Development Status :: 5 - Production/Stable
Classifier: Environment :: Web Environment
Classifier: Intended Audience :: Developers
Classifier: License :: OSI Approved :: MIT License
Classifier: Operating System :: OS Independent
Classifier: Programming Language :: Python
Classifier: Programming Language :: Python :: 2
Classifier: Programming Language :: Python :: 2.6
Classifier: Programming Language :: Python :: 2.7
Classifier: Programming Language :: Python :: 3
Classifier: Programming Language :: Python :: 3.3
Classifier: Framework :: Django
